filterlists_api/__init__.py
filterlists_api/api_client.py
filterlists_api/api_response.py
filterlists_api/configuration.py
filterlists_api/exceptions.py
filterlists_api/py.typed
filterlists_api/rest.py
filterlists_api/api/__init__.py
filterlists_api/api/filter_lists_api.py
filterlists_api/api/languages_api.py
filterlists_api/api/licenses_api.py
filterlists_api/api/maintainers_api.py
filterlists_api/api/software_api.py
filterlists_api/api/syntaxes_api.py
filterlists_api/api/tags_api.py
filterlists_api/models/__init__.py
filterlists_api/models/filter_lists_directory_application_queries_get_languages_response.py
filterlists_api/models/filter_lists_directory_application_queries_get_licenses_response.py
filterlists_api/models/filter_lists_directory_application_queries_get_list_details_response.py
filterlists_api/models/filter_lists_directory_application_queries_get_list_details_view_url_response.py
filterlists_api/models/filter_lists_directory_application_queries_get_lists_response.py
filterlists_api/models/filter_lists_directory_application_queries_get_maintainers_response.py
filterlists_api/models/filter_lists_directory_application_queries_get_software_response.py
filterlists_api/models/filter_lists_directory_application_queries_get_syntaxes_response.py
filterlists_api/models/filter_lists_directory_application_queries_get_tags_response.py
filterlists_api-1.0.10.dist-info/METADATA
filterlists_api-1.0.10.dist-info/WHEEL
filterlists_api-1.0.10.dist-info/top_level.txt
filterlists_api-1.0.10.dist-info/RECORD
